python_service_builder-2.4.1.dist-info/licenses/LICENSE
service_framework/__init__.py
service_framework/__init_test.py
service_framework/service_builder.py
service_framework/service_finder.py
service_framework/services.py
service_framework/services_test.py
service_framework/update_services.py
python_service_builder-2.4.1.dist-info/METADATA
python_service_builder-2.4.1.dist-info/WHEEL
python_service_builder-2.4.1.dist-info/top_level.txt
python_service_builder-2.4.1.dist-info/RECORD
